ai_model_task/__init__.py
ai_model_task/base/__init__.py
ai_model_task/base/ParamsAwareBaseModel.py
ai_model_task/task/chat.py
ai_model_task/task/code_generation.py
ai_model_task/task/paint.py
ai_model_task/task/question_answering.py
ai_model_task/task/reading_comprehension.py
ai_model_task/task/summary.py
ai_model_task/task/table_question_answering.py
ai_model_task/task/text_generation.py
ai_model_task/task/text_to_speech.py
ai_model_task/task/top_k_similarity.py
ai_model_task/task/translation.py
ai_model_task/task/vector_database.py
ai_model_task/task/word_embedding.py
ai_model_task/task/zero_shot_classification.py
ai_model_task-0.0.1.dev1.dist-info/METADATA
ai_model_task-0.0.1.dev1.dist-info/WHEEL
ai_model_task-0.0.1.dev1.dist-info/RECORD
