Metadata-Version: 2.1
Name: ai-model-task
Version: 0.0.1.dev1
Summary: 
Author: taoyang
Author-email: hackty@163.com
Requires-Python: >=3.10,<4.0
Classifier: Programming Language :: Python :: 3
Classifier: Programming Language :: Python :: 3.10
Classifier: Programming Language :: Python :: 3.11
Classifier: Programming Language :: Python :: 3.12
Requires-Dist: pydantic (>=2.6.4,<3.0.0)
